pydoof/__init__.py
pydoof/base.py
pydoof/helpers.py
pydoof/utils.py
pydoof/management_api/__init__.py
pydoof/management_api/api_client.py
pydoof/management_api/exceptions.py
pydoof/management_api/indices.py
pydoof/management_api/internals.py
pydoof/management_api/items.py
pydoof/management_api/search_engines.py
pydoof/management_api/stats.py
pydoof/search_api/__init__.py
pydoof/search_api/api_client.py
pydoof/search_api/exceptions.py
pydoof/search_api/search.py
pydoof/search_api/stats.py
pydoof-4.3.0.dist-info/licenses/LICENSE
tests/__init__.py
tests/test_helpers.py
tests/management_api/__init__.py
tests/management_api/test_api_client.py
tests/management_api/test_indices.py
tests/management_api/test_items.py
tests/management_api/test_search_engines.py
tests/management_api/test_stats.py
tests/search_api/__init__.py
tests/search_api/test_api_client.py
tests/search_api/test_search.py
tests/search_api/test_stats.py
pydoof-4.3.0.dist-info/METADATA
pydoof-4.3.0.dist-info/WHEEL
pydoof-4.3.0.dist-info/top_level.txt
pydoof-4.3.0.dist-info/RECORD
