Metadata-Version: 2.4
Name: PyDoof
Version: 4.3.0
Summary: Doofinder's search & management API client
Home-page: https://github.com/doofinder/pydoof
Author: Doofinder
Author-email: support@doofinder.com
Classifier: Development Status :: 5 - Production/Stable
Classifier: Intended Audience :: Developers
Classifier: License :: OSI Approved :: MIT License
Classifier: Programming Language :: Python :: 3.6
Classifier: Topic :: Internet :: WWW/HTTP :: Indexing/Search
Requires-Python: >=3.6.7
License-File: LICENSE
Requires-Dist: requests>=1.2.3
Dynamic: author
Dynamic: author-email
Dynamic: classifier
Dynamic: description
Dynamic: description-content-type
Dynamic: home-page
Dynamic: license-file
Dynamic: requires-dist
Dynamic: requires-python
Dynamic: summary
